{
    "active": "Adwaita-for-Steam",
    "scripts": true,
    "styles": true,
    "updateNotifications": true,
    "accentColor": "DEFAULT_ACCENT_COLOR",
    "conditions": {
        "Skins": {
            "Color Mode": "Dark",
            "Automatic Mode": "no",
            "Background Color Blend": "no",
            "Foreground Color Blend": "no",
            "Color Blend Amount": "50%",
            "Color Blend Color Space": "sRGB",
            "Fluent Reveal": "no",
            "Avatar Shape": "Round",
            "Blur": "Normal",
            "Display Scrollbars": "no",
            "Display Tooltips": "yes",
            "Display Account Avatar": "no",
            "Display Announcements Button": "no",
            "Display Add Game Button": "no",
            "Display VR Button": "no",
            "Display Big Picture Button": "no",
            "Display URL Bar": "no",
            "Download Bar Width": "Normal",
            "Display Add Shelf Button": "no",
            "Display What's New Section": "no",
            "Display Time Divisions": "yes"
        },
        "Adwaita-for-Steam": {
            "Color theme": "catppuccin-mocha",
            "Font": "Adwaita",
            "Window controls theme": "Adwaita",
            "Window controls layout": "Adwaita",
            "Remove rounded corners": "no",
            "Hide What's New shelf": "no",
            "Show Library sidebar on hover": "no",
            "Login QR code": "Show"
        }
    },
    "colors": {
        "Skins": {
            "--custom-color-background": "24, 47, 57",
            "--custom-color-foreground": "67, 107, 127",
            "--custom-color-ingame": "35, 165, 90",
            "--custom-color-online": "35, 165, 90",
            "--custom-color-away": "240, 178, 50",
            "--custom-color-disturb": "242, 63, 67",
            "--custom-color-offline": "128, 132, 142"
        },
        "Adwaita-for-Steam": {
            "--adw-accent-bg-rgb": "53, 132, 228",
            "--adw-accent-fg-rgb": "255, 255, 255",
            "--adw-accent-rgb": "120, 174, 237",
            "--adw-destructive-bg-rgb": "192, 28, 40",
            "--adw-destructive-fg-rgb": "255, 255, 255",
            "--adw-destructive-rgb": "255, 123, 99",
            "--adw-success-bg-rgb": "38, 162, 105",
            "--adw-success-fg-rgb": "255, 255, 255",
            "--adw-success-rgb": "143, 240, 164",
            "--adw-warning-bg-rgb": "205, 147, 9",
            "--adw-warning-fg-rgb": "0, 0, 0",
            "--adw-warning-rgb": "248, 228, 92",
            "--adw-error-bg-rgb": "192, 28, 40",
            "--adw-error-fg-rgb": "255, 255, 255",
            "--adw-error-rgb": "255, 123, 99",
            "--adw-window-bg-rgb": "34, 34, 38",
            "--adw-window-fg-rgb": "255, 255, 255",
            "--adw-view-bg-rgb": "29, 29, 32",
            "--adw-view-fg-rgb": "255, 255, 255",
            "--adw-headerbar-bg-rgb": "46, 46, 50",
            "--adw-headerbar-fg-rgb": "255, 255, 255",
            "--adw-headerbar-border-rgb": "255, 255, 255",
            "--adw-headerbar-shade-rgb": "0, 0, 6",
            "--adw-headerbar-darker-shade-rgb": "0, 0, 12",
            "--adw-sidebar-bg-rgb": "46, 46, 50",
            "--adw-sidebar-fg-rgb": "255, 255, 255",
            "--adw-sidebar-backdrop-rgb": "40, 40, 44",
            "--adw-sidebar-shade-rgb": "0, 0, 6",
            "--adw-secondary-sidebar-bg-rgb": "40, 40, 44",
            "--adw-secondary-sidebar-fg-rgb": "255, 255, 255",
            "--adw-secondary-sidebar-backdrop-rgb": "37, 37, 41",
            "--adw-secondary-sidebar-shade-rgb": "0, 0, 6",
            "--adw-card-bg-rgb": "255, 255, 255",
            "--adw-card-fg-rgb": "255, 255, 255",
            "--adw-card-shade-rgb": "0, 0, 6",
            "--adw-dialog-bg-rgb": "54, 54, 58",
            "--adw-dialog-fg-rgb": "255, 255, 255",
            "--adw-popover-bg-rgb": "54, 54, 58",
            "--adw-popover-fg-rgb": "255, 255, 255",
            "--adw-popover-shade-rgb": "0, 0, 6",
            "--adw-banner-bg-rgb": "125, 125, 131",
            "--adw-banner-fg-rgb": "255, 255, 255",
            "--adw-thumbnail-bg-rgb": "57, 57, 61",
            "--adw-thumbnail-fg-rgb": "255, 255, 255",
            "--adw-shade-rgb": "0, 0, 6",
            "--adw-user-offline-rgb": "128, 128, 128",
            "--adw-user-online-rgb": "120, 174, 237",
            "--adw-user-ingame-rgb": "143, 240, 164"
        }
    }
}